artify/__init__.py
artify/__main__.py
artify/archive.py
artify/change_version.py
artify/changelog.py
artify/config.txt
artify/dbautomate.py
artify/deploy.py
artify/extract_commands.py
artify/generate_file.py
artify/initialize.py
artify/nexus.py
artify/syncrepo.py
artify/utilities.py
artify-1.10.9.dist-info/METADATA
artify-1.10.9.dist-info/WHEEL
artify-1.10.9.dist-info/entry_points.txt
artify-1.10.9.dist-info/top_level.txt
artify-1.10.9.dist-info/RECORD
