Metadata-Version: 2.1
Name: artify
Version: 1.10.9
Summary: Upload to Nexus, Upload files to hooks, Modify version number, Sync to GitLab type repository, Extract command from Git commit message, Create SonarQube project, Generate template files and Create archives 
Home-page: https://github.com/stewiejnr
Author: Stewartium
Author-email: stewartium1@gmail.com
License: MIT
Classifier: License :: OSI Approved :: MIT License
Classifier: Programming Language :: Python :: 3
Classifier: Programming Language :: Python :: 3.7
Classifier: Programming Language :: Python :: Implementation :: PyPy
Requires-Dist: requests
